binject/__init__.py
binject/cli.py
binject/patch_apk.py
binject-1.0.2.dist-info/METADATA
binject-1.0.2.dist-info/WHEEL
binject-1.0.2.dist-info/entry_points.txt
binject-1.0.2.dist-info/top_level.txt
binject-1.0.2.dist-info/RECORD
