Metadata-Version: 2.4
Name: binject
Version: 1.0.2
Summary: Binject: inject shared object to apk
Author-email: Praveen P <prvnyoutub@gmail.com>
Project-URL: Homepage, https://github.com/prvnprk/binject
Classifier: Programming Language :: Python :: 3
Classifier: Operating System :: OS Independent
Requires-Python: >=3.7
Requires-Dist: rich
Requires-Dist: androguard
